ippy/__init__.py
ippy/ippy.py
ippy-0.3.7.dist-info/AUTHORS.rst
ippy-0.3.7.dist-info/LICENSE
ippy-0.3.7.dist-info/METADATA
ippy-0.3.7.dist-info/WHEEL
ippy-0.3.7.dist-info/top_level.txt
ippy-0.3.7.dist-info/RECORD
