Metadata-Version: 2.1
Name: ippy
Version: 0.3.7
Summary: Parallel testing of IP addresses and domains in python.
Home-page: https://github.com/shivammathur/ippy
Author: Shivam Mathur
Author-email: shivam_jpr@hotmail.com
License: MIT license
Download-URL: https://github.com/shivammathur/ippy/archive/0.3.5.tar.gz
Keywords: ippy
Platform: UNKNOWN
Classifier: Development Status :: 4 - Beta
Classifier: Intended Audience :: Developers
Classifier: License :: OSI Approved :: MIT License
Classifier: Natural Language :: English
Classifier: Programming Language :: Python :: 2.7
Classifier: Programming Language :: Python :: 3.3
Classifier: Programming Language :: Python :: 3.4
Classifier: Programming Language :: Python :: 3.5
Classifier: Programming Language :: Python :: 3.6
Classifier: Programming Language :: Python :: 3.7
Classifier: Programming Language :: Python :: 3.8
Classifier: Topic :: Software Development :: Libraries
Classifier: Topic :: Software Development :: Libraries :: Python Modules
Classifier: Topic :: System :: Networking
Requires-Dist: pingparsing (==0.6.0)
Requires-Dist: future (>=0.16.0)
